kraken_async_api/__init__.py
kraken_async_api/config.py
kraken_async_api/constants.py
kraken_async_api/exchange.py
kraken_async_api/rest.py
kraken_async_api/websocket.py
kraken_async_api-0.1.1b1.dist-info/LICENSE.txt
kraken_async_api-0.1.1b1.dist-info/METADATA
kraken_async_api-0.1.1b1.dist-info/WHEEL
kraken_async_api-0.1.1b1.dist-info/top_level.txt
kraken_async_api-0.1.1b1.dist-info/RECORD
