Metadata-Version: 2.1
Name: kraken-async-api
Version: 0.1.1b1
Summary: Asynchronous Websockets API for the Kraken Cryptocurrency Exchange
Home-page: https://github.com/nickjfenton/kraken-async-api
Author: nickjfenton
Author-email: nickjfenton@yahoo.co.uk
License: MIT
Platform: UNKNOWN
Classifier: Development Status :: 4 - Beta
Classifier: Intended Audience :: Developers
Classifier: License :: OSI Approved :: MIT License
Classifier: Programming Language :: Python :: 3
Classifier: Programming Language :: Python :: 3.4
Classifier: Programming Language :: Python :: 3.5
Classifier: Programming Language :: Python :: 3.6
Classifier: Programming Language :: Python :: 3.7
Classifier: Programming Language :: Python :: 3.8
Classifier: Programming Language :: Python :: 3.9
Requires-Python: >=3.4.0
License-File: LICENSE.txt
Requires-Dist: aiohttp
Requires-Dist: websockets
